cuse/__init__.py
cuse/computer.py
cuse/debug_viewer.py
cuse-0.0.1.dist-info/METADATA
cuse-0.0.1.dist-info/WHEEL
cuse-0.0.1.dist-info/licenses/LICENSE
cuse-0.0.1.dist-info/RECORD
