Metadata-Version: 2.4
Name: cuse
Version: 0.0.1
Summary: Remote control of a computer
License-Expression: MIT
License-File: LICENSE
Requires-Python: >=3.12
Requires-Dist: httpx>=0.25.1
